[
  {
    "key": "claimPermissionsStore",
    "contentType": "application/vnd.marain.tenancy.enrollment.configurationitem.azureblobstorage.v3",
    "configuration": {
      "accountName": "<storage-account-name>",
      "accessKeyInKeyVault": {
        "vaultName": "<key-vault-name>",
        "secretName": "<storage-account-key-secret-name>"
      },
      "container": "<tenant-specific-container-for-claim-permissions>"
    }
  },
  {
    "key": "resourceAccessRuleSetsStore",
    "contentType": "application/vnd.marain.tenancy.enrollment.configurationitem.azureblobstorage.v3",
    "configuration": {
      "accountName": "<storage-account-name>",
      "accessKeyInKeyVault": {
        "vaultName": "<key-vault-name>",
        "secretName": "<storage-account-key-secret-name>"
      },
      "container": "<tenant-specific-container-for-resource-access-rule-sets>"
    }
  }
]